nova_pg/__init__.py
nova_pg/config.py
nova_pg/toolbox.py
nova_pg/utils.py
nova_pg-0.2.4.dist-info/METADATA
nova_pg-0.2.4.dist-info/WHEEL
nova_pg-0.2.4.dist-info/top_level.txt
nova_pg-0.2.4.dist-info/RECORD
