Metadata-Version: 2.4
Name: nova-pg
Version: 0.2.4
Summary: PostgreSQL utilities
Author: Lorenzo Santarsieri
License: MIT
Requires-Python: >=3.10
Requires-Dist: psycopg2>=2.9
Requires-Dist: pandas>=2.3.3
